<annotation>
	<folder>dataset 2</folder>
	<filename>IMG_20200513_005738.jpg</filename>
	<path>D:\fyp\dataset\dataset 2\IMG_20200513_005738.jpg</path>
	<source>
		<database>Unknown</database>
	</source>
	<size>
		<width>1280</width>
		<height>720</height>
		<depth>3</depth>
	</size>
	<segmented>0</segmented>
	<object>
		<name>snake</name>
		<pose>Unspecified</pose>
		<truncated>0</truncated>
		<difficult>0</difficult>
		<bndbox>
			<xmin>625</xmin>
			<ymin>114</ymin>
			<xmax>694</xmax>
			<ymax>223</ymax>
		</bndbox>
	</object>
	<object>
		<name>snake</name>
		<pose>Unspecified</pose>
		<truncated>0</truncated>
		<difficult>0</difficult>
		<bndbox>
			<xmin>616</xmin>
			<ymin>463</ymin>
			<xmax>720</xmax>
			<ymax>545</ymax>
		</bndbox>
	</object>
</annotation>
